pretix_pages/__init__.py
pretix_pages/apps.py
pretix_pages/models.py
pretix_pages/signals.py
pretix_pages/urls.py
pretix_pages/views.py
pretix_pages/locale/django.pot
pretix_pages/locale/ar/LC_MESSAGES/django.mo
pretix_pages/locale/ar/LC_MESSAGES/django.po
pretix_pages/locale/ca/LC_MESSAGES/django.mo
pretix_pages/locale/ca/LC_MESSAGES/django.po
pretix_pages/locale/cs/LC_MESSAGES/django.mo
pretix_pages/locale/cs/LC_MESSAGES/django.po
pretix_pages/locale/da/LC_MESSAGES/django.mo
pretix_pages/locale/da/LC_MESSAGES/django.po
pretix_pages/locale/de/LC_MESSAGES/django.mo
pretix_pages/locale/de/LC_MESSAGES/django.po
pretix_pages/locale/de_Informal/.gitkeep
pretix_pages/locale/de_Informal/LC_MESSAGES/django.mo
pretix_pages/locale/de_Informal/LC_MESSAGES/django.po
pretix_pages/locale/el/LC_MESSAGES/django.mo
pretix_pages/locale/el/LC_MESSAGES/django.po
pretix_pages/locale/es/LC_MESSAGES/django.mo
pretix_pages/locale/es/LC_MESSAGES/django.po
pretix_pages/locale/fi/LC_MESSAGES/django.mo
pretix_pages/locale/fi/LC_MESSAGES/django.po
pretix_pages/locale/fr/LC_MESSAGES/django.mo
pretix_pages/locale/fr/LC_MESSAGES/django.po
pretix_pages/locale/gl/LC_MESSAGES/django.mo
pretix_pages/locale/gl/LC_MESSAGES/django.po
pretix_pages/locale/hr/LC_MESSAGES/django.mo
pretix_pages/locale/hr/LC_MESSAGES/django.po
pretix_pages/locale/it/LC_MESSAGES/django.mo
pretix_pages/locale/it/LC_MESSAGES/django.po
pretix_pages/locale/ja/LC_MESSAGES/django.mo
pretix_pages/locale/ja/LC_MESSAGES/django.po
pretix_pages/locale/lv/LC_MESSAGES/django.mo
pretix_pages/locale/lv/LC_MESSAGES/django.po
pretix_pages/locale/nl/LC_MESSAGES/django.mo
pretix_pages/locale/nl/LC_MESSAGES/django.po
pretix_pages/locale/nl_Informal/LC_MESSAGES/django.mo
pretix_pages/locale/nl_Informal/LC_MESSAGES/django.po
pretix_pages/locale/pl/LC_MESSAGES/django.mo
pretix_pages/locale/pl/LC_MESSAGES/django.po
pretix_pages/locale/pl_Informal/LC_MESSAGES/django.mo
pretix_pages/locale/pl_Informal/LC_MESSAGES/django.po
pretix_pages-1.6.3.dist-info/LICENSE
pretix_pages-1.6.3.dist-info/METADATA
pretix_pages-1.6.3.dist-info/WHEEL
pretix_pages-1.6.3.dist-info/entry_points.txt
pretix_pages-1.6.3.dist-info/top_level.txt
pretix_pages-1.6.3.dist-info/RECORD
