Metadata-Version: 2.1
Name: pretix-pages
Version: 1.6.3
Summary: pretix plugin that allows you to add static pages to your event site, for example for a FAQ, terms of service, etc.
Author-email: pretix team <support@pretix.eu>
Maintainer-email: pretix team <support@pretix.eu>
License: Copyright 2017 Raphael Michel
Project-URL: homepage, https://github.com/pretix/pretix-pages
Keywords: pretix
Requires-Python: >=3.9
License-File: LICENSE
